hydra_tui/__init__.py
hydra_tui/cli.py
hydra_tui/tui/__init__.py
hydra_tui/tui/app.py
hydra_tui/tui/models.py
hydra_tui/tui/widgets/__init__.py
hydra_tui/tui/widgets/command_bar.py
hydra_tui/tui/widgets/config_tree.py
hydra_tui/tui/widgets/confirm_screen.py
hydra_tui/tui/widgets/status_bar.py
hydra_plugins/hydra_intercept_launcher/__init__.py
hydra_plugins/hydra_intercept_launcher/launcher.py
hydra_tui-0.1.1.dist-info/WHEEL
hydra_tui-0.1.1.dist-info/entry_points.txt
hydra_tui-0.1.1.dist-info/METADATA
hydra_tui-0.1.1.dist-info/RECORD
