Metadata-Version: 2.3
Name: hydra-tui
Version: 0.1.1
Summary: Hydra TUI for inspecting and overriding Hydra configurations
Author: Alexander Kovrigin
Author-email: Alexander Kovrigin <alexander.kovrigin@jetbrains.com>
Requires-Dist: hydra-core>=1.3.2
Requires-Dist: omegaconf>=2.3.0
Requires-Dist: rich>=13.0.0
Requires-Dist: textual>=0.30.0
Requires-Python: >=3.10
